penny_ante/__about__.py
penny_ante/__init__.py
penny_ante/bet.py
penny_ante/betting_rules.py
penny_ante/chips.py
penny_ante/croupier.py
penny_ante/dealer.py
penny_ante/game.py
penny_ante/layout.py
penny_ante/player.py
penny_ante/space.py
penny_ante/table.py
penny_ante/wheel.py
penny_ante-1.0.0.dist-info/METADATA
penny_ante-1.0.0.dist-info/WHEEL
penny_ante-1.0.0.dist-info/entry_points.txt
penny_ante-1.0.0.dist-info/licenses/LICENSE.txt
penny_ante-1.0.0.dist-info/RECORD
