Metadata-Version: 2.4
Name: penny-ante
Version: 1.0.0
Summary: A Python roulette wheel game simulator with realistic game architecture
Project-URL: Documentation, https://github.com/huntsberg/python_penny-ante#readme
Project-URL: Issues, https://github.com/huntsberg/python_penny-ante/issues
Project-URL: Source, https://github.com/huntsberg/python_penny-ante
Author-email: Peter Bowen <peter@bowenfamily.org>
License-Expression: MIT
License-File: LICENSE.txt
Keywords: betting,casino,gambling,game,roulette,simulation,wheel
Classifier: Development Status :: 5 - Production/Stable
Classifier: Programming Language :: Python
Classifier: Programming Language :: Python :: 3.10
Classifier: Programming Language :: Python :: 3.11
Classifier: Programming Language :: Python :: 3.12
Classifier: Programming Language :: Python :: Implementation :: CPython
Classifier: Programming Language :: Python :: Implementation :: PyPy
Requires-Python: >=3.10
